{"interfaceLanguages":{"swift":[{"children":[{"title":"Package","type":"groupMarker"},{"path":"\/documentation\/sdglogic\/sdgcornerstone","title":"SDGCornerstone","type":"article"},{"title":"Structures","type":"groupMarker"},{"children":[{"title":"Operators","type":"groupMarker"},{"path":"\/documentation\/sdglogic\/nilliteral\/=_(_:_:)","title":"static func ≠ <T>(T?, NilLiteral) -> Bool","type":"op"},{"title":"Initializers","type":"groupMarker"},{"path":"\/documentation\/sdglogic\/nilliteral\/init(nilliteral:)","title":"init(nilLiteral: Void)","type":"init"}],"path":"\/documentation\/sdglogic\/nilliteral","title":"NilLiteral","type":"struct"},{"title":"Variables","type":"groupMarker"},{"path":"\/documentation\/sdglogic\/falsch","title":"var falsch: Bool","type":"var"},{"path":"\/documentation\/sdglogic\/wahr","title":"var wahr: Bool","type":"var"},{"title":"Operators","type":"groupMarker"},{"path":"\/documentation\/sdglogic\/=_(_:_:)-3370l","title":"func ≠ <A, B, C, D, E>((A, B, C, D, E), (A, B, C, D, E)) -> Bool","type":"op"},{"path":"\/documentation\/sdglogic\/=_(_:_:)-6n0yu","title":"func ≠ <A, B, C, D, E, F>((A, B, C, D, E, F), (A, B, C, D, E, F)) -> Bool","type":"op"},{"path":"\/documentation\/sdglogic\/=_(_:_:)-7bj3k","title":"func ≠ (Any.Type?, Any.Type?) -> Bool","type":"op"},{"path":"\/documentation\/sdglogic\/=_(_:_:)-7efum","title":"func ≠ <A, B, C, D>((A, B, C, D), (A, B, C, D)) -> Bool","type":"op"},{"path":"\/documentation\/sdglogic\/=_(_:_:)-897fy","title":"func ≠ <A, B, C>((A, B, C), (A, B, C)) -> Bool","type":"op"},{"path":"\/documentation\/sdglogic\/=_(_:_:)-8h1qd","title":"func ≠ <A, B>((A, B), (A, B)) -> Bool","type":"op"},{"title":"Type Aliases","type":"groupMarker"},{"path":"\/documentation\/sdglogic\/vergleichbar","title":"Vergleichbar","type":"typealias"},{"path":"\/documentation\/sdglogic\/____","title":"בו״ל","type":"typealias"}],"path":"\/documentation\/sdglogic","title":"SDGLogic","type":"module"}]},"schemaVersion":{"major":0,"minor":1,"patch":1}}